setup.cfg
setup.py
captcha2/__init__.py
captcha2/captcha2.py
captcha2.egg-info/PKG-INFO
captcha2.egg-info/SOURCES.txt
captcha2.egg-info/dependency_links.txt
captcha2.egg-info/requires.txt
captcha2.egg-info/top_level.txt