Metadata-Version: 1.1
Name: captcha2
Version: 0.0.1
Summary: An upload to 2captcha.com library
Home-page: https://github.com/nikoladang/2captcha
Author: Nikola Dang
Author-email: ducthinhdt@gmail.com
License: UNKNOWN
Download-URL: https://github.com/nikoladang/2captcha/tarball/0.1
Keywords: 2captcha,captcha,uploading,automation,resolving,automate
Platform: UNKNOWN
Classifier: Development Status :: 5 - Production/Stable
Classifier: Intended Audience :: Developers
Classifier: Natural Language :: English
Classifier: License :: OSI Approved :: MIT License
Classifier: Operating System :: OS Independent
Classifier: Programming Language :: Python
Classifier: Programming Language :: Python :: 2
Classifier: Programming Language :: Python :: 2.6
Classifier: Programming Language :: Python :: 2.7
Classifier: Programming Language :: Python :: 3
Classifier: Programming Language :: Python :: 3.3
Classifier: Programming Language :: Python :: 3.4
Classifier: Programming Language :: Python :: 3.5
Classifier: Programming Language :: Python :: Implementation :: CPython
Classifier: Programming Language :: Python :: Implementation :: PyPy
Classifier: Topic :: Software Development :: Libraries :: Python Modules
